jmeter_metrics/__init__.py
jmeter_metrics/aggregate_results.py
jmeter_metrics/error_results.py
jmeter_metrics/jmetermetrics.py
jmeter_metrics/overview_results.py
jmeter_metrics/runner.py
jmeter_metrics/table_results.py
jmeter_metrics/version.py
jmeter_metrics-1.0.6.dist-info/LICENSE
jmeter_metrics-1.0.6.dist-info/METADATA
jmeter_metrics-1.0.6.dist-info/WHEEL
jmeter_metrics-1.0.6.dist-info/entry_points.txt
jmeter_metrics-1.0.6.dist-info/top_level.txt
jmeter_metrics-1.0.6.dist-info/zip-safe
jmeter_metrics-1.0.6.dist-info/RECORD
