Metadata-Version: 2.1
Name: jmeter-metrics
Version: 1.0.6
Summary: Custom dashboard report for Jmeter
Home-page: https://github.com/adiralashiva8/jmeter-metrics
Author: Shiva Prasad Adirala
Author-email: adiralashiva8@gmail.com
License: MIT
Keywords: Jmeter report
Platform: UNKNOWN
Classifier: Programming Language :: Python
Classifier: Topic :: Software Development :: Testing
Requires-Dist: pandas
Requires-Dist: beautifulsoup4
